mortal_scheduler/__init__.py
mortal_scheduler/scheduler_main.pyd
mortal_scheduler/scheduler_main.so
mortal_scheduler-3.0.0.dist-info/METADATA
mortal_scheduler-3.0.0.dist-info/WHEEL
mortal_scheduler-3.0.0.dist-info/top_level.txt
mortal_scheduler-3.0.0.dist-info/RECORD
