Metadata-Version: 2.1
Name: mortal-scheduler
Version: 3.0.0
Summary: 'mortal工具集::scheduler'
Author: MJ
License: UNKNOWN
Platform: UNKNOWN
Classifier: Programming Language :: Python :: 3
Classifier: License :: OSI Approved :: MIT License
Classifier: Operating System :: OS Independent
Requires-Python: >=3.7
Requires-Dist: apscheduler==3.11.0
